Mathematics/Addition.py
Mathematics/Division.py
Mathematics/Multiplication.py
Mathematics/Subtraction.py
Mathematics/__init__.py
aniket-0.0.3.dist-info/METADATA
aniket-0.0.3.dist-info/WHEEL
aniket-0.0.3.dist-info/top_level.txt
aniket-0.0.3.dist-info/RECORD
