Metadata-Version: 2.1
Name: aniket
Version: 0.0.3
Summary: Mathematics operation package
Home-page: UNKNOWN
Author: Aniket Raghu Gadge
Author-email: <gadgeaniketraghu@gmail.com>
License: UNKNOWN
Keywords: python,first package
Platform: UNKNOWN
Classifier: Development Status :: 3 - Alpha
Classifier: Intended Audience :: Education
Classifier: Programming Language :: Python :: 2
Classifier: Programming Language :: Python :: 3
Classifier: Operating System :: MacOS :: MacOS X
Classifier: Operating System :: Microsoft :: Windows
Requires-Dist: pandas
